docstring_pdf_converter/__init__.py
docstring_pdf_converter/config.py
docstring_pdf_converter/exemplo.py
docstring_pdf_converter/generate_pdf.py
docstring_pdf_converter/main.py
docstring_pdf_converter-1.0.0.dist-info/licenses/LICENSE
tests/__init__.py
tests/test_generate_pdf.py
docstring_pdf_converter-1.0.0.dist-info/METADATA
docstring_pdf_converter-1.0.0.dist-info/WHEEL
docstring_pdf_converter-1.0.0.dist-info/entry_points.txt
docstring_pdf_converter-1.0.0.dist-info/top_level.txt
docstring_pdf_converter-1.0.0.dist-info/RECORD
