Metadata-Version: 2.4
Name: docstring_pdf_converter
Version: 1.0.0
Summary: Uma ferramenta para converter docstrings de módulos Python em PDFs formatados.
Home-page: https://github.com/WenFra005/docstring_pdf_converter
Author: Wendell Francisco
Author-email: wendellfrancisco2005@hotmail.com
Classifier: Programming Language :: Python :: 3
Classifier: License :: OSI Approved :: MIT License
Classifier: Operating System :: OS Independent
Classifier: Intended Audience :: Developers
Classifier: Topic :: Software Development :: Libraries :: Python Modules
Requires-Python: >=3.6
License-File: LICENSE
Requires-Dist: fpdf
Dynamic: author
Dynamic: author-email
Dynamic: classifier
Dynamic: description
Dynamic: description-content-type
Dynamic: home-page
Dynamic: license-file
Dynamic: requires-dist
Dynamic: requires-python
Dynamic: summary
